coala_json/VERSION
coala_json/__init__.py
coala_json/diagnostic.py
coala_json/loader/JsonLoader.py
coala_json/loader/Loader.py
coala_json/loader/__init__.py
coala_json/loader/coalaJsonLoader.py
coala_json/reporters/AppveyorReporter.py
coala_json/reporters/CheckstyleReporter.py
coala_json/reporters/HtmlReporter.py
coala_json/reporters/JunitReporter.py
coala_json/reporters/ReporterFactory.py
coala_json/reporters/ResultReporter.py
coala_json/reporters/TapReporter.py
coala_json/reporters/__init__.py
coala_json/reporters/cli/__init__.py
coala_json/reporters/cli/cli.py
coala_json-0.1.3.dist-info/LICENSE
coala_json-0.1.3.dist-info/METADATA
coala_json-0.1.3.dist-info/WHEEL
coala_json-0.1.3.dist-info/dependency_links.txt
coala_json-0.1.3.dist-info/entry_points.txt
coala_json-0.1.3.dist-info/top_level.txt
coala_json-0.1.3.dist-info/RECORD
